lua_kernel/__init__.py
lua_kernel/__main__.py
lua_kernel/images.py
lua_kernel/install.py
lua_kernel/kernel.py
lua_kernel/kernel0.py
lua_kernel/utils.py
nb_lua_kernel-1.0.0.dev1.dist-info/DESCRIPTION.rst
nb_lua_kernel-1.0.0.dev1.dist-info/METADATA
nb_lua_kernel-1.0.0.dev1.dist-info/RECORD
nb_lua_kernel-1.0.0.dev1.dist-info/WHEEL
nb_lua_kernel-1.0.0.dev1.dist-info/metadata.json
nb_lua_kernel-1.0.0.dev1.dist-info/top_level.txt
