Metadata-Version: 2.0
Name: nb-lua-kernel
Version: 1.0.0.dev1
Summary: A Lua Kernel for ERAS Jupyter Notebook
Home-page: https://git.tecgraf.puc-rio.br/mjulia/eras-notebook
Author: The ERAS Development Team
Author-email: pypa-dev@googlegroups.com
License: MIT
Keywords: jupyter kernel lua
Platform: UNKNOWN
Classifier: Development Status :: 3 - Alpha
Classifier: Intended Audience :: Developers
Classifier: Topic :: Software Development :: Libraries :: Python Modules
Classifier: License :: OSI Approved :: MIT License
Classifier: Programming Language :: Python :: 2
Classifier: Programming Language :: Python :: 2.7
Classifier: Programming Language :: Python :: 3
Classifier: Programming Language :: Python :: 3.3
Classifier: Programming Language :: Python :: 3.4
Classifier: Programming Language :: Python :: 3.5
